<!DOCTYPE struts PUBLIC
"-//Apache Software Foundation//DTD Struts Configuration 2.0//EN"
"http://struts.apache.org/dtds/struts-2.0.dtd">

<!-- Author: sulic -->

<struts>
    <!-- Add your configuration elements here -->
    <package name="public" namespace="/public" extends="struts-default">

        <interceptors>
            <interceptor name="initem" class="com.rsc.moneta.interceptor.InitEntityManager"/>
            <interceptor-stack name="main">
                <interceptor-ref name="defaultStack"/>
                <interceptor-ref name="initem"/>
             </interceptor-stack>
        </interceptors>
        <default-interceptor-ref name="main" />

        <action name="Login" class="com.rsc.moneta.action.site.Login">
            <result name="private" type="redirectAction">../private/</result>
            <result name="admin" type="redirectAction">../admin/</result>
            <result name="login">/pages/public/login.jsp</result>
        </action>

        <action name="Logout" class="com.rsc.moneta.action.site.Logout">            
            <result>/</result>
        </action>       
    </package>
</struts>
