<!DOCTYPE struts PUBLIC
"-//Apache Software Foundation//DTD Struts Configuration 2.0//EN"
"http://struts.apache.org/dtds/struts-2.0.dtd">

<!-- Author: sulic -->

<struts>
    <!-- Add your configuration elements here -->
    <package name="private" namespace="/private" extends="struts-default">

        <interceptors>
            <interceptor name="initem" class="com.rsc.moneta.interceptor.InitEntityManager"/>
            <interceptor-stack name="main">
                <interceptor-ref name="defaultStack"/>
                <interceptor-ref name="initem"/>
             </interceptor-stack>
        </interceptors>
        <default-interceptor-ref name="main" />

        <action name="ChangeCashOrderStatusForm">
            <result>/pages/private/changeOrderStatusForm.jsp</result>
        </action>

        <action name="ChangeCashOrderStatus" class="com.rsc.moneta.action.admin.ChangeCashOrderStatus">
            <result name="success" type="redirectAction">ViewCashOrderList</result>
            <result name="error" type="redirectAction">ViewCashOrderList</result>
            <result name="next" type="redirectAction">ViewNextUnprocessedCashOrder</result>
        </action>

        <action name="ViewCashOrderList" class="com.rsc.moneta.action.admin.ViewCashOrderList">
            <result>/pages/private/viewCashOrderList.jsp</result>
        </action>

        <action name="ViewCashOrder" class="com.rsc.moneta.action.admin.ViewCashOrder">
            <result>/pages/private/viewCashOrder.jsp</result>
        </action>

        <action name="ViewNextUnprocessedCashOrder" class="com.rsc.moneta.action.admin.ViewCashOrder" method="nextUnprocessedCashOrder">
            <result name="success">/pages/private/viewCashOrder.jsp</result>
            <result name="error" type="redirectAction">ViewCashOrderList</result>
        </action>

    </package>
</struts>
